toml_union/__init__.py
toml_union/toml_union.py
toml_union-1.0.4.dist-info/LICENSE
toml_union-1.0.4.dist-info/METADATA
toml_union-1.0.4.dist-info/WHEEL
toml_union-1.0.4.dist-info/entry_points.txt
toml_union-1.0.4.dist-info/top_level.txt
toml_union-1.0.4.dist-info/RECORD
