Metadata-Version: 2.1
Name: toml-union
Version: 1.0.4
Summary: Utils to merge *.toml files with conflicts highlighting
Home-page: https://github.com/PasaOpasen/toml-union
Author: Demetry Pascal
Author-email: qtckpuhdsa@gmail.com
Maintainer: Demetry Pascal
License: MIT
Keywords: toml,merge
Classifier: Programming Language :: Python :: 3.8
Classifier: License :: OSI Approved :: MIT License
Classifier: Operating System :: OS Independent
Classifier: Topic :: Software Development :: Libraries :: Python Modules
License-File: LICENSE
Requires-Dist: toml
